envs_manager/__about__.py
envs_manager/__init__.py
envs_manager/api.py
envs_manager/cli.py
envs_manager/manager.py
envs_manager/backends/__init__.py
envs_manager/backends/conda_like_interface.py
envs_manager/backends/venv_interface.py
envs_manager/tests/__init__.py
envs_manager/tests/test_cli.py
envs_manager/tests/test_manager.py
envs_manager/tests/env_files/conda-like-files/linux_conda_export_env.yml
envs_manager/tests/env_files/conda-like-files/linux_conda_import_env.yml
envs_manager/tests/env_files/conda-like-files/macos_conda_export_env.yml
envs_manager/tests/env_files/conda-like-files/macos_conda_import_env.yml
envs_manager/tests/env_files/conda-like-files/win_conda_export_env.yml
envs_manager/tests/env_files/conda-like-files/win_conda_import_env.yml
envs_manager/tests/env_files/venv-files/venv_export_env.txt
envs_manager/tests/env_files/venv-files/venv_import_env.txt
envs_manager-0.1.3.dist-info/METADATA
envs_manager-0.1.3.dist-info/WHEEL
envs_manager-0.1.3.dist-info/entry_points.txt
envs_manager-0.1.3.dist-info/licenses/LICENSE
envs_manager-0.1.3.dist-info/RECORD
