Metadata-Version: 2.1
Name: envs-manager
Version: 0.1.3
Summary: A manager for Python environments and packages managers
Project-URL: Documentation, https://github.com/spyder-ide/envs-manager#readme
Project-URL: Issues, https://github.com/spyder-ide/envs-manager/issues
Project-URL: Source, https://github.com/spyder-ide/envs-manager
Author: Spyder Development Team and envs-manager contributors
Author-email: Spyder Development Team and envs-manager contributors <spyder.python@gmail.com>
License: MIT
License-File: LICENSE
Classifier: Development Status :: 2 - Pre-Alpha
Classifier: Programming Language :: Python
Classifier: Programming Language :: Python :: 3.7
Classifier: Programming Language :: Python :: 3.8
Classifier: Programming Language :: Python :: 3.9
Classifier: Programming Language :: Python :: 3.10
Classifier: Programming Language :: Python :: Implementation :: CPython
Requires-Python: >=3.7
Requires-Dist: pyyaml
Requires-Dist: requests
Provides-Extra: pre-commit
Requires-Dist: pre-commit; extra == 'pre-commit'
Provides-Extra: test
Requires-Dist: pytest; extra == 'test'
Requires-Dist: pytest-cov; extra == 'test'
